[
  {
    "Abbreviation": "AFK",
    "Definition": "Away From Keyboard"
  },
  {
    "Abbreviation": "BRB",
    "Definition": "Be Right Back"
  },
  {
    "Abbreviation": "CMIIW",
    "Definition": "Correct me if i'm wrong"
  },
  {
    "Abbreviation": "IKR",
    "Definition": "I know, right"
  },
  {
    "Abbreviation": "ILY",
    "Definition": "I love you"
  },
  {
    "Abbreviation": "IRL",
    "Definition": "In Real Life"
  },
  {
    "Abbreviation": "IYKYK",
    "Definition": "If You Know You Know"
  },
  {
    "Abbreviation": "LFG",
    "Definition": "let's freaking go"
  },
  {
    "Abbreviation": "LMFAO",
    "Definition": "Laughing my freaking *a* off"
  },
  {
    "Abbreviation": "LMK",
    "Definition": "Let me know"
  },
  {
    "Abbreviation": "LOL",
    "Definition": "Laugh out loud"
  },
  {
    "Abbreviation": "LTR",
    "Definition": "Left To Right"
  },
  {
    "Abbreviation": "NVM",
    "Definition": "Never mind"
  },
  {
    "Abbreviation": "OFC",
    "Definition": "Of course"
  },
  {
    "Abbreviation": "ROFL",
    "Definition": "Rolling on floor laughing"
  },
  {
    "Abbreviation": "RTL",
    "Definition": "Right To Left"
  },
  {
    "Abbreviation": "SMH",
    "Definition": "Shaking my head"
  },
  {
    "Abbreviation": "STFU",
    "Definition": "Shut the *freak* up"
  },
  {
    "Abbreviation": "TTYL",
    "Definition": "Talk to you later"
  },
  {
    "Abbreviation": "TYSM",
    "Definition": "Thank You So Much",
    "Usage": "",
    "Example": "<a href=\"https://www.cyberdefinitions.com/definitions/TYSM.html\">Cyber Definitions</a>"
  },
  {
    "Abbreviation": "TYVM",
    "Definition": "Thank you very much"
  },
  {
    "Abbreviation": "YOLO",
    "Definition": "You only live once"
  }
]